setup.cfg
setup.py
util.py
brute/__init__.py
brute/__main__.py
brute/scrape.py
brute/status.py
brute/submit.py
brute/version.py
cmdline_brute.egg-info/PKG-INFO
cmdline_brute.egg-info/SOURCES.txt
cmdline_brute.egg-info/dependency_links.txt
cmdline_brute.egg-info/entry_points.txt
cmdline_brute.egg-info/requires.txt
cmdline_brute.egg-info/top_level.txt