Metadata-Version: 1.0
Name: cmdline-brute
Version: 0.4
Summary: BRUTE FORCE grid search
Home-page: https://bitbucket.org/noandrews/brute
Author: Nicholas Andrews
Author-email: noandrews@gmail.com
License: MIT
Platform: UNKNOWN
